C_kernels/__init__.py
C_kernels/setup.py
C_kernels/test.py
hcr_nn/__init__.py
hcr_nn/basis.py
hcr_nn/density.py
hcr_nn/layers.py
hcr_nn/layers_optimized.py
hcr_nn/models.py
hcr_nn/neuron.py
hcr_nn-1.0.4.dist-info/METADATA
hcr_nn-1.0.4.dist-info/WHEEL
hcr_nn-1.0.4.dist-info/entry_points.txt
hcr_nn-1.0.4.dist-info/top_level.txt
hcr_nn-1.0.4.dist-info/RECORD
