Metadata-Version: 2.4
Name: hcr_nn
Version: 1.0.4
Summary: Package implementing Hierarchical Correlation Reconstruction Methodologies
Requires-Dist: numpy>=1.26.4
Requires-Dist: matplotlib>=3.10.1
Requires-Dist: scipy>=1.13.1
Requires-Dist: torch>=2.7.0
Requires-Dist: pandas>=2.3.0
Dynamic: description
Dynamic: description-content-type
Dynamic: requires-dist
Dynamic: summary
